xarray_regex/__init__.py
xarray_regex/file_finder.py
xarray_regex/library.py
xarray_regex/matcher.py
xarray_regex-0.2.2.dist-info/LICENSE
xarray_regex-0.2.2.dist-info/METADATA
xarray_regex-0.2.2.dist-info/WHEEL
xarray_regex-0.2.2.dist-info/top_level.txt
xarray_regex-0.2.2.dist-info/RECORD
