Metadata-Version: 2.1
Name: xarray-regex
Version: 0.2.2
Summary: Find files using regular expression to feed them to Xarray.
Home-page: https://github.com/Descanonge/xarray-regex
Author: Clément Haëck
Author-email: clement.haeck@posteo.net
License: UNKNOWN
Project-URL: Source, https://github.com/Descanonge/xarray-regex
Project-URL: Documentation, https://xarray-regex.readthedocs.io
Keywords: xarray regex files
Platform: UNKNOWN
Classifier: License :: OSI Approved :: MIT License
Classifier: Programming Language :: Python :: 3.7
Classifier: Operating System :: OS Independent
Requires-Python: >=3.7
